Full_Adder/four_bit_full_adder/one_bit_full_adder.v
module full_adder (
    input a,
    input b,
    input cin,
    output s,
    output cout
);
    assign s = a^b^cin;
    assign cout = (a&b) | (cin & (a^b));
    
endmodule

Full_Adder/four_bit_full_adder/four_bit_full_adder.v
module four_bit_full_adder(
    input [3:0] a,
    input [3:0] b,
    input cin,
    output [3:0] s,
    output cout
);

    wire c1,c2,c3;

    full_adder fa0(a[0],b[0],cin,s[0],c1);
    full_adder fa1(a[1],b[1],c1,s[1],c2);
    full_adder fa2(a[2],b[2],c2,s[2],c3);
    full_adder fa3(a[3],b[3],c3,s[3],cout);
endmodule

Full_Adder/four_bit_full_adder/four_bit_full_adder_tb.v
`timescale 1ns/1ps

module four_bit_full_adder_tb;
    reg [3:0] a,b;
    reg cin;
    wire [3:0] s;
    wire cout;

    four_bit_full_adder uut(
        .a(a),
        .b(b),
        .cin(cin),
        .s(s),
        .cout(cout)
    );


    integer i,j;

    initial begin
        $dumpfile("wave.vcd");
        $dumpvars(0, four_bit_full_adder_tb);
        $display("a   b   cin | cout    s  | Result");
        $display("---------------------------------");
        for(i=0; i<16; i=i+1)
        begin
            for(j=0; j<16; j=j+1)
            begin
                cin = 0;
                {a} = i[3:0];
                {b} = j[3:0];
                #10;
                // $display("%d %d | %d", a,b,{cout,s});
                $display("%4b %4b %b | %4b %b | %d", a, b, cin, cout, s, {cout,s});  //In binary
                // $display("%d %d %d | %d %d", a, b, cin, s, cout);     // In decimal
            end
        end
        $finish;
    end

endmodule

Full_Adder/four_bit_full_adder/wave.vcd
$date
	Fri Apr 17 02:52:05 2026
$end
$version
	Icarus Verilog
$end
$timescale
	1ps
$end
$scope module four_bit_full_adder_tb $end
$var wire 4 ! s [3:0] $end
$var wire 1 " cout $end
$var reg 4 # a [3:0] $end
$var reg 4 $ b [3:0] $end
$var reg 1 % cin $end
$var integer 32 & i [31:0] $end
$var integer 32 ' j [31:0] $end
$scope module uut $end
$var wire 4 ( a [3:0] $end
$var wire 4 ) b [3:0] $end
$var wire 1 % cin $end
$var wire 4 * s [3:0] $end
$var wire 1 " cout $end
$var wire 1 + c3 $end
$var wire 1 , c2 $end
$var wire 1 - c1 $end
$scope module fa0 $end
$var wire 1 . a $end
$var wire 1 / b $end
$var wire 1 % cin $end
$var wire 1 - cout $end
$var wire 1 0 s $end
$upscope $end
$scope module fa1 $end
$var wire 1 1 a $end
$var wire 1 2 b $end
$var wire 1 - cin $end
$var wire 1 , cout $end
$var wire 1 3 s $end
$upscope $end
$scope module fa2 $end
$var wire 1 4 a $end
$var wire 1 5 b $end
$var wire 1 , cin $end
$var wire 1 + cout $end
$var wire 1 6 s $end
$upscope $end
$scope module fa3 $end
$var wire 1 7 a $end
$var wire 1 8 b $end
$var wire 1 + cin $end
$var wire 1 " cout $end
$var wire 1 9 s $end
$upscope $end
$upscope $end
$upscope $end
$enddefinitions $end
$comment Show the parameter values. $end
$dumpall
$end
#0
$dumpvars
09
08
07
06
05
04
03
02
01
00
0/
0.
0-
0,
0+
b0 *
b0 )
b0 (
b0 '
b0 &
0%
b0 $
b0 #
0"
b0 !
$end
#10000
b1 !
b1 *
10
1/
b1 $
b1 )
b1 '
#20000
00
b10 !
b10 *
13
0/
12
b10 $
b10 )
b10 '
#30000
b11 !
b11 *
10
1/
b11 $
b11 )
b11 '
#40000
00
03
b100 !
b100 *
16
0/
02
15
b100 $
b100 )
b100 '
#50000
b101 !
b101 *
10
1/
b101 $
b101 )
b101 '
#60000
00
b110 !
b110 *
13
0/
12
b110 $
b110 )
b110 '
#70000
b111 !
b111 *
10
1/
b111 $
b111 )
b111 '
#80000
00
03
06
b1000 !
b1000 *
19
0/
02
05
18
b1000 $
b1000 )
b1000 '
#90000
b1001 !
b1001 *
10
1/
b1001 $
b1001 )
b1001 '
#100000
00
b1010 !
b1010 *
13
0/
12
b1010 $
b1010 )
b1010 '
#110000
b1011 !
b1011 *
10
1/
b1011 $
b1011 )
b1011 '
#120000
00
03
b1100 !
b1100 *
16
0/
02
15
b1100 $
b1100 )
b1100 '
#130000
b1101 !
b1101 *
10
1/
b1101 $
b1101 )
b1101 '
#140000
00
b1110 !
b1110 *
13
0/
12
b1110 $
b1110 )
b1110 '
#150000
b1111 !
b1111 *
10
1/
b1111 $
b1111 )
b1111 '
#160000
03
06
b1 !
b1 *
09
0/
02
05
08
1.
b0 $
b0 )
b1 #
b1 (
b1 &
b0 '
#170000
13
b10 !
b10 *
00
1-
1/
b1 $
b1 )
b1 '
#180000
06
0,
10
0-
b11 !
b11 *
13
0/
12
b10 $
b10 )
b10 '
#190000
16
1,
03
b100 !
b100 *
00
1-
1/
b11 $
b11 )
b11 '
#200000
09
0,
0+
10
0-
03
b101 !
b101 *
16
0/
02
15
b100 $
b100 )
b100 '
#210000
13
b110 !
b110 *
00
1-
1/
b101 $
b101 )
b101 '
#220000
09
0+
16
0,
10
0-
b111 !
b111 *
13
0/
12
b110 $
b110 )
b110 '
#230000
19
1+
06
1,
03
b1000 !
b1000 *
00
1-
1/
b111 $
b111 )
b111 '
#240000
0,
0+
0"
10
0-
03
06
b1001 !
b1001 *
19
0/
02
05
18
b1000 $
b1000 )
b1000 '
#250000
13
b1010 !
b1010 *
00
1-
1/
b1001 $
b1001 )
b1001 '
#260000
06
0,
10
0-
b1011 !
b1011 *
13
0/
12
b1010 $
b1010 )
b1010 '
#270000
16
1,
03
b1100 !
b1100 *
00
1-
1/
b1011 $
b1011 )
b1011 '
#280000
0"
19
0,
0+
10
0-
03
b1101 !
b1101 *
16
0/
02
15
b1100 $
b1100 )
b1100 '
#290000
13
b1110 !
b1110 *
00
1-
1/
b1101 $
b1101 )
b1101 '
#300000
0"
19
0+
16
0,
10
0-
b1111 !
b1111 *
13
0/
12
b1110 $
b1110 )
b1110 '
#310000
1"
09
1+
06
1,
03
b0 !
b0 *
00
1-
1/
b1111 $
b1111 )
b1111 '
#320000
0,
0+
0"
13
06
b10 !
b10 *
09
0-
0/
02
05
08
0.
11
b0 $
b0 )
b10 #
b10 (
b10 &
b0 '
#330000
b11 !
b11 *
10
1/
b1 $
b1 )
b1 '
#340000
16
00
b100 !
b100 *
03
1,
0/
12
b10 $
b10 )
b10 '
#350000
b101 !
b101 *
10
1/
b11 $
b11 )
b11 '
#360000
09
0+
00
13
0,
b110 !
b110 *
16
0/
02
15
b100 $
b100 )
b100 '
#370000
b111 !
b111 *
10
1/
b101 $
b101 )
b101 '
#380000
19
1+
06
00
b1000 !
b1000 *
03
1,
0/
12
b110 $
b110 )
b110 '
#390000
b1001 !
b1001 *
10
1/
b111 $
b111 )
b111 '
#400000
0+
0"
00
13
0,
06
b1010 !
b1010 *
19
0/
02
05
18
b1000 $
b1000 )
b1000 '
#410000
b1011 !
b1011 *
10
1/
b1001 $
b1001 )
b1001 '
#420000
16
00
b1100 !
b1100 *
03
1,
0/
12
b1010 $
b1010 )
b1010 '
#430000
b1101 !
b1101 *
10
1/
b1011 $
b1011 )
b1011 '
#440000
0"
19
0+
00
13
0,
b1110 !
b1110 *
16
0/
02
15
b1100 $
b1100 )
b1100 '
#450000
b1111 !
b1111 *
10
1/
b1101 $
b1101 )
b1101 '
#460000
1"
09
1+
06
00
b0 !
b0 *
03
1,
0/
12
b1110 $
b1110 )
b1110 '
#470000
b1 !
b1 *
10
1/
b1111 $
b1111 )
b1111 '
#480000
0+
0"
13
0,
06
b11 !
b11 *
09
0/
02
05
08
1.
b0 $
b0 )
b11 #
b11 (
b11 &
b0 '
#490000
16
1,
03
b100 !
b100 *
00
1-
1/
b1 $
b1 )
b1 '
#500000
10
0-
b101 !
b101 *
03
0/
12
b10 $
b10 )
b10 '
#510000
13
b110 !
b110 *
00
1-
1/
b11 $
b11 )
b11 '
#520000
0,
09
0+
10
0-
13
b111 !
b111 *
16
0/
02
15
b100 $
b100 )
b100 '
#530000
19
1+
06
1,
03
b1000 !
b1000 *
00
1-
1/
b101 $
b101 )
b101 '
#540000
10
0-
b1001 !
b1001 *
03
0/
12
b110 $
b110 )
b110 '
#550000
13
b1010 !
b1010 *
00
1-
1/
b111 $
b111 )
b111 '
#560000
0,
0+
0"
10
0-
13
06
b1011 !
b1011 *
19
0/
02
05
18
b1000 $
b1000 )
b1000 '
#570000
16
1,
03
b1100 !
b1100 *
00
1-
1/
b1001 $
b1001 )
b1001 '
#580000
10
0-
b1101 !
b1101 *
03
0/
12
b1010 $
b1010 )
b1010 '
#590000
13
b1110 !
b1110 *
00
1-
1/
b1011 $
b1011 )
b1011 '
#600000
0"
0,
19
0+
10
0-
13
b1111 !
b1111 *
16
0/
02
15
b1100 $
b1100 )
b1100 '
#610000
1"
09
1+
06
1,
03
b0 !
b0 *
00
1-
1/
b1101 $
b1101 )
b1101 '
#620000
10
0-
b1 !
b1 *
03
0/
12
b1110 $
b1110 )
b1110 '
#630000
13
b10 !
b10 *
00
1-
1/
b1111 $
b1111 )
b1111 '
#640000
0+
0"
03
16
b100 !
b100 *
09
0-
0,
0/
02
05
08
0.
01
14
b0 $
b0 )
b100 #
b100 (
b100 &
b0 '
#650000
b101 !
b101 *
10
1/
b1 $
b1 )
b1 '
#660000
00
b110 !
b110 *
13
0/
12
b10 $
b10 )
b10 '
#670000
b111 !
b111 *
10
1/
b11 $
b11 )
b11 '
#680000
19
00
03
b1000 !
b1000 *
06
1+
0/
02
15
b100 $
b100 )
b100 '
#690000
b1001 !
b1001 *
10
1/
b101 $
b101 )
b101 '
#700000
00
b1010 !
b1010 *
13
0/
12
b110 $
b110 )
b110 '
#710000
b1011 !
b1011 *
10
1/
b111 $
b111 )
b111 '
#720000
0"
00
03
16
0+
b1100 !
b1100 *
19
0/
02
05
18
b1000 $
b1000 )
b1000 '
#730000
b1101 !
b1101 *
10
1/
b1001 $
b1001 )
b1001 '
#740000
00
b1110 !
b1110 *
13
0/
12
b1010 $
b1010 )
b1010 '
#750000
b1111 !
b1111 *
10
1/
b1011 $
b1011 )
b1011 '
#760000
1"
09
00
03
b0 !
b0 *
06
1+
0/
02
15
b1100 $
b1100 )
b1100 '
#770000
b1 !
b1 *
10
1/
b1101 $
b1101 )
b1101 '
#780000
00
b10 !
b10 *
13
0/
12
b1110 $
b1110 )
b1110 '
#790000
b11 !
b11 *
10
1/
b1111 $
b1111 )
b1111 '
#800000
0"
03
16
0+
b101 !
b101 *
09
0/
02
05
08
1.
b0 $
b0 )
b101 #
b101 (
b101 &
b0 '
#810000
13
b110 !
b110 *
00
1-
1/
b1 $
b1 )
b1 '
#820000
09
0+
16
0,
10
0-
b111 !
b111 *
13
0/
12
b10 $
b10 )
b10 '
#830000
19
1+
06
1,
03
b1000 !
b1000 *
00
1-
1/
b11 $
b11 )
b11 '
#840000
0,
10
0-
03
b1001 !
b1001 *
06
0/
02
15
b100 $
b100 )
b100 '
#850000
13
b1010 !
b1010 *
00
1-
1/
b101 $
b101 )
b101 '
#860000
06
0,
10
0-
b1011 !
b1011 *
13
0/
12
b110 $
b110 )
b110 '
#870000
16
1,
03
b1100 !
b1100 *
00
1-
1/
b111 $
b111 )
b111 '
#880000
0+
0,
0"
10
0-
03
16
b1101 !
b1101 *
19
0/
02
05
18
b1000 $
b1000 )
b1000 '
#890000
13
b1110 !
b1110 *
00
1-
1/
b1001 $
b1001 )
b1001 '
#900000
0"
19
0+
16
0,
10
0-
b1111 !
b1111 *
13
0/
12
b1010 $
b1010 )
b1010 '
#910000
1"
09
1+
06
1,
03
b0 !
b0 *
00
1-
1/
b1011 $
b1011 )
b1011 '
#920000
0,
10
0-
03
b1 !
b1 *
06
0/
02
15
b1100 $
b1100 )
b1100 '
#930000
13
b10 !
b10 *
00
1-
1/
b1101 $
b1101 )
b1101 '
#940000
06
0,
10
0-
b11 !
b11 *
13
0/
12
b1110 $
b1110 )
b1110 '
#950000
16
1,
03
b100 !
b100 *
00
1-
1/
b1111 $
b1111 )
b1111 '
#960000
0+
0,
0"
13
16
b110 !
b110 *
09
0-
0/
02
05
08
0.
11
b0 $
b0 )
b110 #
b110 (
b110 &
b0 '
#970000
b111 !
b111 *
10
1/
b1 $
b1 )
b1 '
#980000
19
1+
06
00
b1000 !
b1000 *
03
1,
0/
12
b10 $
b10 )
b10 '
#990000
b1001 !
b1001 *
10
1/
b11 $
b11 )
b11 '
#1000000
00
13
0,
b1010 !
b1010 *
06
0/
02
15
b100 $
b100 )
b100 '
#1010000
b1011 !
b1011 *
10
1/
b101 $
b101 )
b101 '
#1020000
16
00
b1100 !
b1100 *
03
1,
0/
12
b110 $
b110 )
b110 '
#1030000
b1101 !
b1101 *
10
1/
b111 $
b111 )
b111 '
#1040000
0+
0"
00
13
0,
16
b1110 !
b1110 *
19
0/
02
05
18
b1000 $
b1000 )
b1000 '
#1050000
b1111 !
b1111 *
10
1/
b1001 $
b1001 )
b1001 '
#1060000
1"
09
1+
06
00
b0 !
b0 *
03
1,
0/
12
b1010 $
b1010 )
b1010 '
#1070000
b1 !
b1 *
10
1/
b1011 $
b1011 )
b1011 '
#1080000
00
13
0,
b10 !
b10 *
06
0/
02
15
b1100 $
b1100 )
b1100 '
#1090000
b11 !
b11 *
10
1/
b1101 $
b1101 )
b1101 '
#1100000
16
00
b100 !
b100 *
03
1,
0/
12
b1110 $
b1110 )
b1110 '
#1110000
b101 !
b101 *
10
1/
b1111 $
b1111 )
b1111 '
#1120000
0+
0"
13
0,
16
b111 !
b111 *
09
0/
02
05
08
1.
b0 $
b0 )
b111 #
b111 (
b111 &
b0 '
#1130000
19
1+
06
1,
03
b1000 !
b1000 *
00
1-
1/
b1 $
b1 )
b1 '
#1140000
10
0-
b1001 !
b1001 *
03
0/
12
b10 $
b10 )
b10 '
#1150000
13
b1010 !
b1010 *
00
1-
1/
b11 $
b11 )
b11 '
#1160000
0,
10
0-
13
b1011 !
b1011 *
06
0/
02
15
b100 $
b100 )
b100 '
#1170000
16
1,
03
b1100 !
b1100 *
00
1-
1/
b101 $
b101 )
b101 '
#1180000
10
0-
b1101 !
b1101 *
03
0/
12
b110 $
b110 )
b110 '
#1190000
13
b1110 !
b1110 *
00
1-
1/
b111 $
b111 )
b111 '
#1200000
0+
0,
0"
10
0-
13
16
b1111 !
b1111 *
19
0/
02
05
18
b1000 $
b1000 )
b1000 '
#1210000
1"
09
1+
06
1,
03
b0 !
b0 *
00
1-
1/
b1001 $
b1001 )
b1001 '
#1220000
10
0-
b1 !
b1 *
03
0/
12
b1010 $
b1010 )
b1010 '
#1230000
13
b10 !
b10 *
00
1-
1/
b1011 $
b1011 )
b1011 '
#1240000
0,
10
0-
13
b11 !
b11 *
06
0/
02
15
b1100 $
b1100 )
b1100 '
#1250000
16
1,
03
b100 !
b100 *
00
1-
1/
b1101 $
b1101 )
b1101 '
#1260000
10
0-
b101 !
b101 *
03
0/
12
b1110 $
b1110 )
b1110 '
#1270000
13
b110 !
b110 *
00
1-
1/
b1111 $
b1111 )
b1111 '
#1280000
0"
03
06
b1000 !
b1000 *
19
0-
0,
0+
0/
02
05
08
0.
01
04
17
b0 $
b0 )
b1000 #
b1000 (
b1000 &
b0 '
#1290000
b1001 !
b1001 *
10
1/
b1 $
b1 )
b1 '
#1300000
00
b1010 !
b1010 *
13
0/
12
b10 $
b10 )
b10 '
#1310000
b1011 !
b1011 *
10
1/
b11 $
b11 )
b11 '
#1320000
00
03
b1100 !
b1100 *
16
0/
02
15
b100 $
b100 )
b100 '
#1330000
b1101 !
b1101 *
10
1/
b101 $
b101 )
b101 '
#1340000
00
b1110 !
b1110 *
13
0/
12
b110 $
b110 )
b110 '
#1350000
b1111 !
b1111 *
10
1/
b111 $
b111 )
b111 '
#1360000
00
03
06
b0 !
b0 *
09
1"
0/
02
05
18
b1000 $
b1000 )
b1000 '
#1370000
b1 !
b1 *
10
1/
b1001 $
b1001 )
b1001 '
#1380000
00
b10 !
b10 *
13
0/
12
b1010 $
b1010 )
b1010 '
#1390000
b11 !
b11 *
10
1/
b1011 $
b1011 )
b1011 '
#1400000
00
03
b100 !
b100 *
16
0/
02
15
b1100 $
b1100 )
b1100 '
#1410000
b101 !
b101 *
10
1/
b1101 $
b1101 )
b1101 '
#1420000
00
b110 !
b110 *
13
0/
12
b1110 $
b1110 )
b1110 '
#1430000
b111 !
b111 *
10
1/
b1111 $
b1111 )
b1111 '
#1440000
03
06
b1001 !
b1001 *
19
0"
0/
02
05
08
1.
b0 $
b0 )
b1001 #
b1001 (
b1001 &
b0 '
#1450000
13
b1010 !
b1010 *
00
1-
1/
b1 $
b1 )
b1 '
#1460000
06
0,
10
0-
b1011 !
b1011 *
13
0/
12
b10 $
b10 )
b10 '
#1470000
16
1,
03
b1100 !
b1100 *
00
1-
1/
b11 $
b11 )
b11 '
#1480000
0"
19
0,
0+
10
0-
03
b1101 !
b1101 *
16
0/
02
15
b100 $
b100 )
b100 '
#1490000
13
b1110 !
b1110 *
00
1-
1/
b101 $
b101 )
b101 '
#1500000
0"
19
0+
16
0,
10
0-
b1111 !
b1111 *
13
0/
12
b110 $
b110 )
b110 '
#1510000
1"
09
1+
06
1,
03
b0 !
b0 *
00
1-
1/
b111 $
b111 )
b111 '
#1520000
0,
0+
10
0-
03
06
b1 !
b1 *
09
0/
02
05
18
b1000 $
b1000 )
b1000 '
#1530000
13
b10 !
b10 *
00
1-
1/
b1001 $
b1001 )
b1001 '
#1540000
06
0,
10
0-
b11 !
b11 *
13
0/
12
b1010 $
b1010 )
b1010 '
#1550000
16
1,
03
b100 !
b100 *
00
1-
1/
b1011 $
b1011 )
b1011 '
#1560000
09
0,
0+
10
0-
03
b101 !
b101 *
16
0/
02
15
b1100 $
b1100 )
b1100 '
#1570000
13
b110 !
b110 *
00
1-
1/
b1101 $
b1101 )
b1101 '
#1580000
09
0+
16
0,
10
0-
b111 !
b111 *
13
0/
12
b1110 $
b1110 )
b1110 '
#1590000
19
1+
06
1,
03
b1000 !
b1000 *
00
1-
1/
b1111 $
b1111 )
b1111 '
#1600000
0"
0,
0+
13
06
b1010 !
b1010 *
19
0-
0/
02
05
08
0.
11
b0 $
b0 )
b1010 #
b1010 (
b1010 &
b0 '
#1610000
b1011 !
b1011 *
10
1/
b1 $
b1 )
b1 '
#1620000
16
00
b1100 !
b1100 *
03
1,
0/
12
b10 $
b10 )
b10 '
#1630000
b1101 !
b1101 *
10
1/
b11 $
b11 )
b11 '
#1640000
0"
19
0+
00
13
0,
b1110 !
b1110 *
16
0/
02
15
b100 $
b100 )
b100 '
#1650000
b1111 !
b1111 *
10
1/
b101 $
b101 )
b101 '
#1660000
1"
09
1+
06
00
b0 !
b0 *
03
1,
0/
12
b110 $
b110 )
b110 '
#1670000
b1 !
b1 *
10
1/
b111 $
b111 )
b111 '
#1680000
0+
00
13
0,
06
b10 !
b10 *
09
0/
02
05
18
b1000 $
b1000 )
b1000 '
#1690000
b11 !
b11 *
10
1/
b1001 $
b1001 )
b1001 '
#1700000
16
00
b100 !
b100 *
03
1,
0/
12
b1010 $
b1010 )
b1010 '
#1710000
b101 !
b101 *
10
1/
b1011 $
b1011 )
b1011 '
#1720000
09
0+
00
13
0,
b110 !
b110 *
16
0/
02
15
b1100 $
b1100 )
b1100 '
#1730000
b111 !
b111 *
10
1/
b1101 $
b1101 )
b1101 '
#1740000
19
1+
06
00
b1000 !
b1000 *
03
1,
0/
12
b1110 $
b1110 )
b1110 '
#1750000
b1001 !
b1001 *
10
1/
b1111 $
b1111 )
b1111 '
#1760000
0"
0+
13
0,
06
b1011 !
b1011 *
19
0/
02
05
08
1.
b0 $
b0 )
b1011 #
b1011 (
b1011 &
b0 '
#1770000
16
1,
03
b1100 !
b1100 *
00
1-
1/
b1 $
b1 )
b1 '
#1780000
10
0-
b1101 !
b1101 *
03
0/
12
b10 $
b10 )
b10 '
#1790000
13
b1110 !
b1110 *
00
1-
1/
b11 $
b11 )
b11 '
#1800000
0"
0,
19
0+
10
0-
13
b1111 !
b1111 *
16
0/
02
15
b100 $
b100 )
b100 '
#1810000
1"
09
1+
06
1,
03
b0 !
b0 *
00
1-
1/
b101 $
b101 )
b101 '
#1820000
10
0-
b1 !
b1 *
03
0/
12
b110 $
b110 )
b110 '
#1830000
13
b10 !
b10 *
00
1-
1/
b111 $
b111 )
b111 '
#1840000
0,
0+
10
0-
13
06
b11 !
b11 *
09
0/
02
05
18
b1000 $
b1000 )
b1000 '
#1850000
16
1,
03
b100 !
b100 *
00
1-
1/
b1001 $
b1001 )
b1001 '
#1860000
10
0-
b101 !
b101 *
03
0/
12
b1010 $
b1010 )
b1010 '
#1870000
13
b110 !
b110 *
00
1-
1/
b1011 $
b1011 )
b1011 '
#1880000
0,
09
0+
10
0-
13
b111 !
b111 *
16
0/
02
15
b1100 $
b1100 )
b1100 '
#1890000
19
1+
06
1,
03
b1000 !
b1000 *
00
1-
1/
b1101 $
b1101 )
b1101 '
#1900000
10
0-
b1001 !
b1001 *
03
0/
12
b1110 $
b1110 )
b1110 '
#1910000
13
b1010 !
b1010 *
00
1-
1/
b1111 $
b1111 )
b1111 '
#1920000
0"
0+
03
16
b1100 !
b1100 *
19
0-
0,
0/
02
05
08
0.
01
14
b0 $
b0 )
b1100 #
b1100 (
b1100 &
b0 '
#1930000
b1101 !
b1101 *
10
1/
b1 $
b1 )
b1 '
#1940000
00
b1110 !
b1110 *
13
0/
12
b10 $
b10 )
b10 '
#1950000
b1111 !
b1111 *
10
1/
b11 $
b11 )
b11 '
#1960000
1"
09
00
03
b0 !
b0 *
06
1+
0/
02
15
b100 $
b100 )
b100 '
#1970000
b1 !
b1 *
10
1/
b101 $
b101 )
b101 '
#1980000
00
b10 !
b10 *
13
0/
12
b110 $
b110 )
b110 '
#1990000
b11 !
b11 *
10
1/
b111 $
b111 )
b111 '
#2000000
00
03
16
0+
b100 !
b100 *
09
0/
02
05
18
b1000 $
b1000 )
b1000 '
#2010000
b101 !
b101 *
10
1/
b1001 $
b1001 )
b1001 '
#2020000
00
b110 !
b110 *
13
0/
12
b1010 $
b1010 )
b1010 '
#2030000
b111 !
b111 *
10
1/
b1011 $
b1011 )
b1011 '
#2040000
19
00
03
b1000 !
b1000 *
06
1+
0/
02
15
b1100 $
b1100 )
b1100 '
#2050000
b1001 !
b1001 *
10
1/
b1101 $
b1101 )
b1101 '
#2060000
00
b1010 !
b1010 *
13
0/
12
b1110 $
b1110 )
b1110 '
#2070000
b1011 !
b1011 *
10
1/
b1111 $
b1111 )
b1111 '
#2080000
0"
03
16
0+
b1101 !
b1101 *
19
0/
02
05
08
1.
b0 $
b0 )
b1101 #
b1101 (
b1101 &
b0 '
#2090000
13
b1110 !
b1110 *
00
1-
1/
b1 $
b1 )
b1 '
#2100000
0"
19
0+
16
0,
10
0-
b1111 !
b1111 *
13
0/
12
b10 $
b10 )
b10 '
#2110000
1"
09
1+
06
1,
03
b0 !
b0 *
00
1-
1/
b11 $
b11 )
b11 '
#2120000
0,
10
0-
03
b1 !
b1 *
06
0/
02
15
b100 $
b100 )
b100 '
#2130000
13
b10 !
b10 *
00
1-
1/
b101 $
b101 )
b101 '
#2140000
06
0,
10
0-
b11 !
b11 *
13
0/
12
b110 $
b110 )
b110 '
#2150000
16
1,
03
b100 !
b100 *
00
1-
1/
b111 $
b111 )
b111 '
#2160000
0+
0,
10
0-
03
16
b101 !
b101 *
09
0/
02
05
18
b1000 $
b1000 )
b1000 '
#2170000
13
b110 !
b110 *
00
1-
1/
b1001 $
b1001 )
b1001 '
#2180000
09
0+
16
0,
10
0-
b111 !
b111 *
13
0/
12
b1010 $
b1010 )
b1010 '
#2190000
19
1+
06
1,
03
b1000 !
b1000 *
00
1-
1/
b1011 $
b1011 )
b1011 '
#2200000
0,
10
0-
03
b1001 !
b1001 *
06
0/
02
15
b1100 $
b1100 )
b1100 '
#2210000
13
b1010 !
b1010 *
00
1-
1/
b1101 $
b1101 )
b1101 '
#2220000
06
0,
10
0-
b1011 !
b1011 *
13
0/
12
b1110 $
b1110 )
b1110 '
#2230000
16
1,
03
b1100 !
b1100 *
00
1-
1/
b1111 $
b1111 )
b1111 '
#2240000
0"
0+
0,
13
16
b1110 !
b1110 *
19
0-
0/
02
05
08
0.
11
b0 $
b0 )
b1110 #
b1110 (
b1110 &
b0 '
#2250000
b1111 !
b1111 *
10
1/
b1 $
b1 )
b1 '
#2260000
1"
09
1+
06
00
b0 !
b0 *
03
1,
0/
12
b10 $
b10 )
b10 '
#2270000
b1 !
b1 *
10
1/
b11 $
b11 )
b11 '
#2280000
00
13
0,
b10 !
b10 *
06
0/
02
15
b100 $
b100 )
b100 '
#2290000
b11 !
b11 *
10
1/
b101 $
b101 )
b101 '
#2300000
16
00
b100 !
b100 *
03
1,
0/
12
b110 $
b110 )
b110 '
#2310000
b101 !
b101 *
10
1/
b111 $
b111 )
b111 '
#2320000
0+
00
13
0,
16
b110 !
b110 *
09
0/
02
05
18
b1000 $
b1000 )
b1000 '
#2330000
b111 !
b111 *
10
1/
b1001 $
b1001 )
b1001 '
#2340000
19
1+
06
00
b1000 !
b1000 *
03
1,
0/
12
b1010 $
b1010 )
b1010 '
#2350000
b1001 !
b1001 *
10
1/
b1011 $
b1011 )
b1011 '
#2360000
00
13
0,
b1010 !
b1010 *
06
0/
02
15
b1100 $
b1100 )
b1100 '
#2370000
b1011 !
b1011 *
10
1/
b1101 $
b1101 )
b1101 '
#2380000
16
00
b1100 !
b1100 *
03
1,
0/
12
b1110 $
b1110 )
b1110 '
#2390000
b1101 !
b1101 *
10
1/
b1111 $
b1111 )
b1111 '
#2400000
0"
0+
13
0,
16
b1111 !
b1111 *
19
0/
02
05
08
1.
b0 $
b0 )
b1111 #
b1111 (
b1111 &
b0 '
#2410000
1"
09
1+
06
1,
03
b0 !
b0 *
00
1-
1/
b1 $
b1 )
b1 '
#2420000
10
0-
b1 !
b1 *
03
0/
12
b10 $
b10 )
b10 '
#2430000
13
b10 !
b10 *
00
1-
1/
b11 $
b11 )
b11 '
#2440000
0,
10
0-
13
b11 !
b11 *
06
0/
02
15
b100 $
b100 )
b100 '
#2450000
16
1,
03
b100 !
b100 *
00
1-
1/
b101 $
b101 )
b101 '
#2460000
10
0-
b101 !
b101 *
03
0/
12
b110 $
b110 )
b110 '
#2470000
13
b110 !
b110 *
00
1-
1/
b111 $
b111 )
b111 '
#2480000
0+
0,
10
0-
13
16
b111 !
b111 *
09
0/
02
05
18
b1000 $
b1000 )
b1000 '
#2490000
19
1+
06
1,
03
b1000 !
b1000 *
00
1-
1/
b1001 $
b1001 )
b1001 '
#2500000
10
0-
b1001 !
b1001 *
03
0/
12
b1010 $
b1010 )
b1010 '
#2510000
13
b1010 !
b1010 *
00
1-
1/
b1011 $
b1011 )
b1011 '
#2520000
0,
10
0-
13
b1011 !
b1011 *
06
0/
02
15
b1100 $
b1100 )
b1100 '
#2530000
16
1,
03
b1100 !
b1100 *
00
1-
1/
b1101 $
b1101 )
b1101 '
#2540000
10
0-
b1101 !
b1101 *
03
0/
12
b1110 $
b1110 )
b1110 '
#2550000
13
b1110 !
b1110 *
00
1-
1/
b1111 $
b1111 )
b1111 '
#2560000
b10000 &
b10000 '
