Sequance_Detector/1011_Sequance_Detector/Moore_Machine_(overlapping)/sq_1011_d.v
module sq_1011_d(
    input wire clk,
    input wire reset,
    input wire din,
    output wire dout
);

reg [2:0] state;
parameter s0 = 3'b000,
          s1 = 3'b001,
          s2 = 3'b010,
          s3 = 3'b011,
          s4 = 3'b100;

always @(posedge clk or posedge reset) begin
    if(reset) begin
        state <= s0;
    end
    else begin
        case(state)
            s0: if (din) state <= s1; else state <= s0;
            s1: if (din) state <= s1; else state <= s2;
            s2: if (din) state <= s3; else state <= s0;
            s3: if (din) state <= s4; else state <= s2;
            s4: if (din) state <= s1; else state <= s2;
            default: state <= s0;
        endcase
    end
end

assign dout = (state==s4);

endmodule




 // answer delay in one cycle


// module sq_1011_d(
//     input wire clk,
//     input wire reset,
//     input wire din,
//     output reg dout
// );

// reg [2:0] state;
// parameter s0 = 3'b000,
//           s1 = 3'b001,
//           s2 = 3'b010,
//           s3 = 3'b011,
//           s4 = 3'b100;

// always @(posedge clk or posedge reset) begin
//     if(reset) begin
//         state <= s0;
//         dout <= 0;
//     end
//     else begin
//         case(state)
//             s0: dout <= 0; if (din) state <= s1; else state <= s0;
//             s1: dout <= 0; if (din) state <= s1; else state <= s2;
//             s2: dout <= 0; if (din) state <= s3; else state <= s0;
//             s3: dout <= 0; if (din) state <= s4; else state <= s2;
//             s4: dout <= 1; if (din) state <= s1; else state <= s2;
//             default: state <= s0;
//         endcase
//     end
// end

// endmodule

Sequance_Detector/1011_Sequance_Detector/Moore_Machine_(overlapping)/sq_1011_d_tb.v
`timescale 1ns/1ps

module sq_1011_d_tb;

    reg clk;
    reg reset;
    reg din;
    wire dout;

    sq_1011_d uut(
        .clk(clk),
        .reset(reset),
        .din(din),
        .dout(dout)
    );

    initial begin
        clk = 1'b0;
        forever #5 clk = ~clk;
    end

    task test_bit(input reg bit);
    begin
        din = bit;
        #10;
    end
    endtask


    initial begin
        $dumpfile("wave.vcd");
        $dumpvars(0, sq_1011_d_tb);
        reset = 1'b1;
        din = 1'b0;
        #5
        reset = 1'b0;

        // dummpy check
        test_bit(1);
        test_bit(0);
        test_bit(0);

        // main check
        test_bit(1);
        test_bit(0);
        test_bit(1);
        test_bit(1);


        test_bit(1);
        test_bit(1);
        test_bit(0);
        test_bit(1);
        test_bit(1);

        test_bit(0);
        test_bit(1);
        test_bit(1);
        test_bit(0);
        test_bit(1);
        test_bit(0);

        $finish;
    end

endmodule

Sequance_Detector/1011_Sequance_Detector/Moore_Machine_(non_overlapping)/wave.vcd
$date
	Thu Apr 16 18:57:14 2026
$end
$version
	Icarus Verilog
$end
$timescale
	1ps
$end
$scope module sq_1011_d_tb $end
$var wire 1 ! dout $end
$var reg 1 " clk $end
$var reg 1 # din $end
$var reg 1 $ reset $end
$scope module uut $end
$var wire 1 " clk $end
$var wire 1 # din $end
$var wire 1 $ reset $end
$var wire 1 ! dout $end
$var parameter 3 % s0 $end
$var parameter 3 & s1 $end
$var parameter 3 ' s2 $end
$var parameter 3 ( s3 $end
$var parameter 3 ) s4 $end
$var reg 3 * state [2:0] $end
$upscope $end
$scope task test_bit $end
$var reg 1 + bit $end
$upscope $end
$upscope $end
$enddefinitions $end
$comment Show the parameter values. $end
$dumpall
b100 )
b11 (
b10 '
b1 &
b0 %
$end
#0
$dumpvars
x+
b0 *
1$
0#
0"
0!
$end
#5000
b1 *
1#
1+
0$
1"
#10000
0"
#15000
b10 *
1"
0#
0+
#20000
0"
#25000
b0 *
1"
#30000
0"
#35000
b1 *
1"
1#
1+
#40000
0"
#45000
b10 *
1"
0#
0+
#50000
0"
#55000
b11 *
1"
1#
1+
#60000
0"
#65000
1!
b100 *
1"
#70000
0"
#75000
0!
b1 *
1"
#80000
0"
#85000
1"
#90000
0"
#95000
b10 *
1"
0#
0+
#100000
0"
#105000
b11 *
1"
1#
1+
#110000
0"
#115000
1!
b100 *
1"
#120000
0"
#125000
0!
b0 *
1"
0#
0+
#130000
0"
#135000
1"
#140000
0"
#145000
b1 *
1"
1#
1+
#150000
0"
#155000
b10 *
1"
0#
0+
#160000
0"
#165000
b11 *
1"
1#
1+
#170000
0"
#175000
b10 *
1"
0#
0+
#180000
0"
#185000
b0 *
1"
