Sequance_Detector/1011_Sequance_Detector/Mealy_Machine_(overlapping)/sq_1011_d.v
module sq_1011_d(
    input wire clk,
    input wire reset,
    input wire din,
    output reg dout
);

 reg [1:0] state;
 parameter s0 = 2'b00,
           s1 = 2'b01,
           s2 = 2'b10,
           s3 = 2'b11;

 always @(posedge clk or posedge reset) begin
    if(reset) begin
        dout <= 1'b0;
        state <= s0;
    end
    else begin
        dout <= 0;
        case(state)
            s0: begin
                if(din)
                    state <=s1;
                else 
                    state <= s0;
            end
            s1 : begin
                if(din) 
                    state <= s1;
                else
                    state <= s2;
            end
            s2 : begin
                if(din)
                    state <= s3;
                else
                    state <= s0;
            end
            s3 : begin
                if(din) begin
                    state <= s1;
                    dout <= 1;
                end
                else
                    state <=s2;
            end
        endcase
    end
 end
endmodule

Sequance_Detector/1010_Sequance_Detector/Mealy_Machine_(overlapping)/sq_1010_d_tb.v
// Testbench for 1011 Mealy non-overlapping sequence detector
module sq_1011_d_tb;

    // Signals
    reg clk;
    reg reset;
    reg din;
    wire dout;

    // Instantiate the design
    sq_1011_d uut (
        .clk(clk),
        .reset(reset),
        .din(din),
        .dout(dout)
    );

    // Clock generation: 10 ns period
    initial begin
        clk = 1'b0;
        forever #5 clk = ~clk;
    end

    task apply_bit(input reg bit_in);
        begin
            din = bit_in;
            #10;
        end
    endtask

    initial begin
        // Initialize inputs
        $dumpfile("wave.vcd");
        $dumpvars(0, sq_1011_d_tb);
        reset = 1'b1;
        din   = 1'b0;

        // Display signal activity
        $monitor("Time = %0t | reset = %b | din = %b | dout = %b", $time, reset, din, dout);

        // Apply reset
        #12;
        reset = 1'b0;

        // Sequence: 1 0 1 1 -> detect
        apply_bit(1'b1);
        apply_bit(1'b0);
        apply_bit(1'b1);
        apply_bit(1'b1);

        // Extra bits: no detect
        apply_bit(1'b0);
        apply_bit(1'b1);
        apply_bit(1'b0);

        // Sequence: 1 0 1 1 -> detect again
        apply_bit(1'b1);
        apply_bit(1'b0);
        apply_bit(1'b1);
        apply_bit(1'b1);

        // Back-to-back stream to show non-overlapping behavior
        // 10111011 should produce two pulses, one for each complete 1011
        apply_bit(1'b1);
        apply_bit(1'b0);
        apply_bit(1'b1);
        apply_bit(1'b1);
        apply_bit(1'b1);
        apply_bit(1'b0);
        apply_bit(1'b1);
        apply_bit(1'b1);

        #20;
        $finish;
    end



endmodule

Sequance_Detector/1011_Sequance_Detector/Mealy_Machine_(overlapping)/wave.vcd
$date
	Thu Apr 16 19:16:44 2026
$end
$version
	Icarus Verilog
$end
$timescale
	1s
$end
$scope module sq_1011_d_tb $end
$var wire 1 ! dout $end
$var reg 1 " clk $end
$var reg 1 # din $end
$var reg 1 $ reset $end
$scope module uut $end
$var wire 1 " clk $end
$var wire 1 # din $end
$var wire 1 $ reset $end
$var parameter 2 % s0 $end
$var parameter 2 & s1 $end
$var parameter 2 ' s2 $end
$var parameter 2 ( s3 $end
$var reg 1 ! dout $end
$var reg 2 ) state [1:0] $end
$upscope $end
$scope task apply_bit $end
$var reg 1 * bit_in $end
$upscope $end
$upscope $end
$enddefinitions $end
$comment Show the parameter values. $end
$dumpall
b11 (
b10 '
b1 &
b0 %
$end
#0
$dumpvars
x*
b0 )
1$
0#
0"
0!
$end
#5
1"
#10
0"
#12
1#
1*
0$
#15
b1 )
1"
#20
0"
#22
0#
0*
#25
b10 )
1"
#30
0"
#32
1#
1*
#35
b11 )
1"
#40
0"
#45
1!
b1 )
1"
#50
0"
#52
0#
0*
#55
b10 )
0!
1"
#60
0"
#62
1#
1*
#65
b11 )
1"
#70
0"
#72
0#
0*
#75
b10 )
1"
#80
0"
#82
1#
1*
#85
b11 )
1"
#90
0"
#92
0#
0*
#95
b10 )
1"
#100
0"
#102
1#
1*
#105
b11 )
1"
#110
0"
#115
1!
b1 )
1"
#120
0"
#125
0!
1"
#130
0"
#132
0#
0*
#135
b10 )
1"
#140
0"
#142
1#
1*
#145
b11 )
1"
#150
0"
#155
1!
b1 )
1"
#160
0"
#165
0!
1"
#170
0"
#172
0#
0*
#175
b10 )
1"
#180
0"
#182
1#
1*
#185
b11 )
1"
#190
0"
#195
1!
b1 )
1"
#200
0"
#205
0!
1"
