Full_Adder/four_bit_full_adder/one_bit_full_adder.v
module full_adder (
    input a,
    input b,
    input cin,
    output s,
    output cout
);
    assign s = a^b^cin;
    assign cout = (a&b) | (cin & (a^b));
endmodule

Full_Adder/One_bit_full_adder/full_adder_tb.v
`timescale 1ns/1ps

module full_adder_tb;
    reg x,y,carry;
    wire carry_out,sum;

// Instantiate DUT (Device Under Test)
full_adder uut (
    .a(x),
    .b(y),
    .cin(carry),
    .s(sum),
    .cout(carry_out)
);


integer i;

initial begin
    $display("x y carry | sum carry_out");
    $display("------------------------------");
    $dumpfile("wave.vcd");
    $dumpvars(2, full_adder_tb);
    for (i=0; i<8 ; i=i+1)
    begin
        {x,y,carry} = i[2:0];
        #10;
        $display("%b %b %b | %b  %b", x, y, carry, sum, carry_out);
    end

    $finish;
end

endmodule

Full_Adder/One_bit_full_adder/wave.vcd
$date
	Wed Apr 15 23:02:31 2026
$end
$version
	Icarus Verilog
$end
$timescale
	1ps
$end
$scope module full_adder_tb $end
$var wire 1 ! sum $end
$var wire 1 " carry_out $end
$var reg 1 # carry $end
$var reg 1 $ x $end
$var reg 1 % y $end
$var integer 32 & i [31:0] $end
$scope module uut $end
$var wire 1 $ a $end
$var wire 1 % b $end
$var wire 1 # cin $end
$var wire 1 " cout $end
$var wire 1 ! s $end
$upscope $end
$upscope $end
$enddefinitions $end
$comment Show the parameter values. $end
$dumpall
$end
#0
$dumpvars
b0 &
0%
0$
0#
0"
0!
$end
#10000
1!
1#
b1 &
#20000
1!
1%
0#
b10 &
#30000
1"
0!
1#
b11 &
#40000
0"
1!
1$
0%
0#
b100 &
#50000
1"
0!
1#
b101 &
#60000
0!
1%
0#
b110 &
#70000
1!
1#
b111 &
#80000
b1000 &
